[
  {
    "ContainingType": "OdontoPrev.Controllers.PostController",
    "Method": "GetPosts",
    "RelativePath": "api/Post",
    "HttpMethod": "GET",
    "IsController": true,
    "Order": 0,
    "Parameters": [],
    "ReturnTypes": [
      {
        "Type": "System.Collections.Generic.IEnumerable\u00601[[OdontoPrev.ViewModels.PostViewModel, Odontoprev \u002B, Version=1.0.0.0, Culture=neutral, PublicKeyToken=null]]",
        "MediaTypes": [
          "text/plain",
          "application/json",
          "text/json"
        ],
        "StatusCode": 200
      }
    ]
  },
  {
    "ContainingType": "OdontoPrev.Controllers.PostController",
    "Method": "CreatePost",
    "RelativePath": "api/Post",
    "HttpMethod": "POST",
    "IsController": true,
    "Order": 0,
    "Parameters": [
      {
        "Name": "postViewModel",
        "Type": "OdontoPrev.ViewModels.PostViewModel",
        "IsRequired": true
      }
    ],
    "ReturnTypes": [
      {
        "Type": "OdontoPrev.ViewModels.PostViewModel",
        "MediaTypes": [
          "text/plain",
          "application/json",
          "text/json"
        ],
        "StatusCode": 200
      }
    ]
  },
  {
    "ContainingType": "OdontoPrev.Controllers.PostController",
    "Method": "GetPost",
    "RelativePath": "api/Post/{id}",
    "HttpMethod": "GET",
    "IsController": true,
    "Order": 0,
    "Parameters": [
      {
        "Name": "id",
        "Type": "System.Int32",
        "IsRequired": true
      }
    ],
    "ReturnTypes": [
      {
        "Type": "OdontoPrev.ViewModels.PostViewModel",
        "MediaTypes": [
          "text/plain",
          "application/json",
          "text/json"
        ],
        "StatusCode": 200
      }
    ]
  },
  {
    "ContainingType": "OdontoPrev.Controllers.PostController",
    "Method": "UpdatePost",
    "RelativePath": "api/Post/{id}",
    "HttpMethod": "PUT",
    "IsController": true,
    "Order": 0,
    "Parameters": [
      {
        "Name": "id",
        "Type": "System.Int32",
        "IsRequired": true
      },
      {
        "Name": "postViewModel",
        "Type": "OdontoPrev.ViewModels.PostViewModel",
        "IsRequired": true
      }
    ],
    "ReturnTypes": []
  },
  {
    "ContainingType": "OdontoPrev.Controllers.PostController",
    "Method": "DeletePost",
    "RelativePath": "api/Post/{id}",
    "HttpMethod": "DELETE",
    "IsController": true,
    "Order": 0,
    "Parameters": [
      {
        "Name": "id",
        "Type": "System.Int32",
        "IsRequired": true
      }
    ],
    "ReturnTypes": []
  }
]